{
  "itemid": "minecraft:enchanted_book",
  "displayname": "{\"text\":\"Enchanted Book\",\"color\":\"white\"}",
  "nbttag": "{\"id\":\"minecraft:enchanted_book\",\"count\":1,\"components\":{\"minecraft:custom_name\":\"{\\\"text\\\":\\\"Enchanted Book\\\",\\\"color\\\":\\\"white\\\"}\",\"minecraft:lore\":[\"{\\\"text\\\":\\\"Dragon Tracer I\\\",\\\"color\\\":\\\"blue\\\"}\",\"{\\\"text\\\":\\\"Arrows home towards dragons if\\\",\\\"color\\\":\\\"gray\\\"}\",\"{\\\"text\\\":\\\"\\\",\\\"extra\\\":[{\\\"text\\\":\\\"they are within \\\",\\\"color\\\":\\\"gray\\\"},{\\\"text\\\":\\\"2 \\\",\\\"color\\\":\\\"green\\\"},{\\\"text\\\":\\\"blocks.\\\",\\\"color\\\":\\\"gray\\\"}]}\",\"{\\\"text\\\":\\\"\\\"}\",\"{\\\"text\\\":\\\"Use this on an item in an Anvil\\\",\\\"color\\\":\\\"gray\\\"}\",\"{\\\"text\\\":\\\"to apply it!\\\",\\\"color\\\":\\\"gray\\\"}\",\"{\\\"text\\\":\\\"\\\"}\",\"{\\\"text\\\":\\\"Source:\\\",\\\"color\\\":\\\"gold\\\"}\",\"{\\\"text\\\":\\\"\\\",\\\"extra\\\":[{\\\"text\\\":\\\"I-V: \\\",\\\"color\\\":\\\"green\\\"},{\\\"text\\\":\\\"Enchantment Table,\\\",\\\"color\\\":\\\"gray\\\"}]}\",\"{\\\"text\\\":\\\"Feather Collection\\\",\\\"color\\\":\\\"gray\\\"}\",\"{\\\"text\\\":\\\"\\\"}\",\"{\\\"text\\\":\\\"Applied To:\\\",\\\"color\\\":\\\"gold\\\"}\",\"{\\\"text\\\":\\\"\\\",\\\"extra\\\":[{\\\"text\\\":\\\"- \\\",\\\"color\\\":\\\"gray\\\"},{\\\"text\\\":\\\"Bow\\\",\\\"color\\\":\\\"white\\\"}]}\",\"{\\\"text\\\":\\\"\\\"}\",\"{\\\"text\\\":\\\"COMMON\\\",\\\"color\\\":\\\"white\\\",\\\"bold\\\":true}\"]}}",
  "damage": 0,
  "lore": [
    "{\"text\":\"Dragon Tracer I\",\"color\":\"blue\"}",
    "{\"text\":\"Arrows home towards dragons if\",\"color\":\"gray\"}",
    "{\"text\":\"\",\"extra\":[{\"text\":\"they are within \",\"color\":\"gray\"},{\"text\":\"2 \",\"color\":\"green\"},{\"text\":\"blocks.\",\"color\":\"gray\"}]}",
    "{\"text\":\"\"}",
    "{\"text\":\"Use this on an item in an Anvil\",\"color\":\"gray\"}",
    "{\"text\":\"to apply it!\",\"color\":\"gray\"}",
    "{\"text\":\"\"}",
    "{\"text\":\"Source:\",\"color\":\"gold\"}",
    "{\"text\":\"\",\"extra\":[{\"text\":\"I-V: \",\"color\":\"green\"},{\"text\":\"Enchantment Table,\",\"color\":\"gray\"}]}",
    "{\"text\":\"Feather Collection\",\"color\":\"gray\"}",
    "{\"text\":\"\"}",
    "{\"text\":\"Applied To:\",\"color\":\"gold\"}",
    "{\"text\":\"\",\"extra\":[{\"text\":\"- \",\"color\":\"gray\"},{\"text\":\"Bow\",\"color\":\"white\"}]}",
    "{\"text\":\"\"}",
    "{\"text\":\"COMMON\",\"color\":\"white\",\"bold\":true}"
  ],
  "internalname": "AIMING;1",
  "parent": "AIMING;4",
  "clickcommand": "",
  "modver": "2.1.0-REL",
  "crafttext": "",
  "infoType": "",
  "format_version": 1,
  "conversion_method": "modern_1215_components",
  "converted_modern": true
}