{
  "itemid": "minecraft:player_head",
  "displayname": "{\"text\":\"Bea (NPC)\",\"color\":\"blue\"}",
  "nbttag": "{\"id\":\"minecraft:player_head\",\"count\":1,\"components\":{\"minecraft:custom_name\":\"{\\\"text\\\":\\\"Bea (NPC)\\\",\\\"color\\\":\\\"blue\\\"}\",\"minecraft:lore\":[\"{\\\"text\\\":\\\"\\\"}\"],\"minecraft:custom_data\":{\"id\":\"BEA_NPC\"},\"minecraft:hide_additional_tooltip\":{}}}",
  "damage": 0,
  "lore": [
    "{\"text\":\"\"}"
  ],
  "internalname": "BEA_NPC",
  "clickcommand": "viewrecipe",
  "modver": "2.1.1-PRE",
  "infoType": "WIKI_URL",
  "info": [
    "https://hypixel-skyblock.fandom.com/wiki/Bea",
    "https://wiki.hypixel.net/Bea"
  ],
  "crafttext": "",
  "x": 31,
  "y": 72,
  "z": -94,
  "island": "hub",
  "recipes": [
    {
      "type": "npc_shop",
      "cost": [
        "SKYBLOCK_COIN:4999",
        "COAL_BLOCK:2",
        "GOLD_BLOCK:2"
      ],
      "result": "BEE;0"
    },
    {
      "type": "npc_shop",
      "cost": [
        "SKYBLOCK_COIN:50000",
        "COAL_BLOCK:128",
        "GOLD_BLOCK:128"
      ],
      "result": "BEE;2"
    },
    {
      "type": "npc_shop",
      "cost": [
        "SKYBLOCK_COIN:200000",
        "ENCHANTED_COAL_BLOCK:1",
        "ENCHANTED_GOLD_BLOCK:1"
      ],
      "result": "BEE;3"
    },
    {
      "type": "npc_shop",
      "cost": [
        "SKYBLOCK_COIN:650000",
        "ENCHANTED_COAL_BLOCK:8",
        "ENCHANTED_GOLD_BLOCK:8"
      ],
      "result": "BEE;4"
    }
  ],
  "format_version": 1,
  "conversion_method": "modern_1215_components",
  "converted_modern": true
}