{
  "itemid": "minecraft:player_head",
  "displayname": "{\"text\":\"Campfire Scion Badge\",\"color\":\"dark_purple\"}",
  "nbttag": "{\"id\":\"minecraft:player_head\",\"count\":1,\"components\":{\"minecraft:custom_name\":\"{\\\"text\\\":\\\"Campfire Scion Badge\\\",\\\"color\\\":\\\"dark_purple\\\"}\",\"minecraft:lore\":[\"{\\\"text\\\":\\\"\\\",\\\"extra\\\":[{\\\"text\\\":\\\"Heal \\\",\\\"color\\\":\\\"gray\\\"},{\\\"text\\\":\\\"38❤ \\\",\\\"color\\\":\\\"red\\\"},{\\\"text\\\":\\\"per second\\\",\\\"color\\\":\\\"gray\\\"}]}\",\"{\\\"text\\\":\\\"while burning.\\\",\\\"color\\\":\\\"gray\\\"}\",\"{\\\"text\\\":\\\"\\\"}\",\"{\\\"text\\\":\\\"Trial of Fire XIX\\\",\\\"color\\\":\\\"gold\\\"}\",\"{\\\"text\\\":\\\"\\\\\\\"Fire guy!\\\\\\\"\\\",\\\"color\\\":\\\"dark_gray\\\",\\\"italic\\\":true}\",\"{\\\"text\\\":\\\"\\\"}\",\"{\\\"text\\\":\\\"EPIC ACCESSORY\\\",\\\"color\\\":\\\"dark_purple\\\",\\\"bold\\\":true}\"],\"minecraft:custom_data\":{\"originTag\":\"FIRE_TRIALS_1\",\"id\":\"CAMPFIRE_TALISMAN_18\"},\"minecraft:hide_additional_tooltip\":{}}}",
  "damage": 0,
  "lore": [
    "{\"text\":\"\",\"extra\":[{\"text\":\"Heal \",\"color\":\"gray\"},{\"text\":\"38❤ \",\"color\":\"red\"},{\"text\":\"per second\",\"color\":\"gray\"}]}",
    "{\"text\":\"while burning.\",\"color\":\"gray\"}",
    "{\"text\":\"\"}",
    "{\"text\":\"Trial of Fire XIX\",\"color\":\"gold\"}",
    "{\"text\":\"\\\"Fire guy!\\\"\",\"color\":\"dark_gray\",\"italic\":true}",
    "{\"text\":\"\"}",
    "{\"text\":\"EPIC ACCESSORY\",\"color\":\"dark_purple\",\"bold\":true}"
  ],
  "internalname": "CAMPFIRE_TALISMAN_18",
  "clickcommand": "",
  "modver": "2.1.0-REL",
  "infoType": "WIKI_URL",
  "info": [
    "https://hypixel-skyblock.fandom.com/wiki/Campfire_Scion_Badge",
    "https://wiki.hypixel.net/Campfire_Scion_Badge"
  ],
  "format_version": 1,
  "conversion_method": "modern_1215_components",
  "converted_modern": true
}