{
  "itemid": "minecraft:golden_sword",
  "displayname": "{\"text\":\"Florid Zombie Sword\",\"color\":\"gold\"}",
  "nbttag": "{\"id\":\"minecraft:golden_sword\",\"count\":1,\"components\":{\"minecraft:custom_name\":\"{\\\"text\\\":\\\"Florid Zombie Sword\\\",\\\"color\\\":\\\"gold\\\"}\",\"minecraft:lore\":[\"{\\\"text\\\":\\\"\\\",\\\"extra\\\":[{\\\"text\\\":\\\"Damage: \\\",\\\"color\\\":\\\"gray\\\"},{\\\"text\\\":\\\"+150\\\",\\\"color\\\":\\\"red\\\"}]}\",\"{\\\"text\\\":\\\"\\\",\\\"extra\\\":[{\\\"text\\\":\\\"Strength: \\\",\\\"color\\\":\\\"gray\\\"},{\\\"text\\\":\\\"+80\\\",\\\"color\\\":\\\"red\\\"}]}\",\"{\\\"text\\\":\\\"\\\",\\\"extra\\\":[{\\\"text\\\":\\\"Intelligence: \\\",\\\"color\\\":\\\"gray\\\"},{\\\"text\\\":\\\"+100\\\",\\\"color\\\":\\\"green\\\"}]}\",\"{\\\"text\\\":\\\"\\\",\\\"extra\\\":[{\\\"text\\\":\\\" \\\"},{\\\"text\\\":\\\"[\\\",\\\"color\\\":\\\"dark_gray\\\"},{\\\"text\\\":\\\"✎\\\",\\\"color\\\":\\\"gray\\\"},{\\\"text\\\":\\\"] [❤]\\\",\\\"color\\\":\\\"dark_gray\\\"}]}\",\"{\\\"text\\\":\\\"\\\"}\",\"{\\\"text\\\":\\\"\\\",\\\"extra\\\":[{\\\"text\\\":\\\"Ability: Instant Heal \\\",\\\"color\\\":\\\"gold\\\"},{\\\"text\\\":\\\"RIGHT CLICK\\\",\\\"color\\\":\\\"yellow\\\",\\\"bold\\\":true}]}\",\"{\\\"text\\\":\\\"\\\",\\\"extra\\\":[{\\\"text\\\":\\\"Heal for \\\",\\\"color\\\":\\\"gray\\\"},{\\\"text\\\":\\\"168 \\\",\\\"color\\\":\\\"red\\\"},{\\\"text\\\":\\\"+ \\\",\\\"color\\\":\\\"gray\\\"},{\\\"text\\\":\\\"5%❤ \\\",\\\"color\\\":\\\"red\\\"},{\\\"text\\\":\\\"and heal players within \\\",\\\"color\\\":\\\"gray\\\"},{\\\"text\\\":\\\"8\\\",\\\"color\\\":\\\"green\\\"}]}\",\"{\\\"text\\\":\\\"\\\",\\\"extra\\\":[{\\\"text\\\":\\\"blocks for \\\",\\\"color\\\":\\\"gray\\\"},{\\\"text\\\":\\\"56❤\\\",\\\"color\\\":\\\"red\\\"},{\\\"text\\\":\\\".\\\",\\\"color\\\":\\\"gray\\\"}]}\",\"{\\\"text\\\":\\\"\\\",\\\"extra\\\":[{\\\"text\\\":\\\"Mana Cost: \\\",\\\"color\\\":\\\"dark_gray\\\"},{\\\"text\\\":\\\"70\\\",\\\"color\\\":\\\"dark_aqua\\\"}]}\",\"{\\\"text\\\":\\\"\\\",\\\"extra\\\":[{\\\"text\\\":\\\"Charges: \\\",\\\"color\\\":\\\"dark_gray\\\"},{\\\"text\\\":\\\"5 \\\",\\\"color\\\":\\\"yellow\\\"},{\\\"text\\\":\\\"/ \\\",\\\"color\\\":\\\"dark_gray\\\"},{\\\"text\\\":\\\"15s\\\",\\\"color\\\":\\\"green\\\"}]}\",\"{\\\"text\\\":\\\"\\\"}\",\"{\\\"text\\\":\\\"\\\",\\\"extra\\\":[{\\\"text\\\":\\\"Gain \\\",\\\"color\\\":\\\"gray\\\"},{\\\"text\\\":\\\"+2 \\\",\\\"color\\\":\\\"green\\\"},{\\\"text\\\":\\\"extra max charges when you\\\",\\\"color\\\":\\\"gray\\\"}]}\",\"{\\\"text\\\":\\\"\\\",\\\"extra\\\":[{\\\"text\\\":\\\"play as a \\\",\\\"color\\\":\\\"gray\\\"},{\\\"text\\\":\\\"Healer \\\",\\\"color\\\":\\\"green\\\"},{\\\"text\\\":\\\"in Dungeons.\\\",\\\"color\\\":\\\"gray\\\"}]}\",\"{\\\"text\\\":\\\"\\\"}\",\"{\\\"text\\\":\\\"This item can be reforged!\\\",\\\"color\\\":\\\"dark_gray\\\"}\",\"{\\\"text\\\":\\\"LEGENDARY SWORD\\\",\\\"color\\\":\\\"gold\\\",\\\"bold\\\":true}\"],\"minecraft:custom_data\":{\"id\":\"FLORID_ZOMBIE_SWORD\"},\"minecraft:hide_additional_tooltip\":{},\"minecraft:unbreakable\":{}}}",
  "damage": 0,
  "lore": [
    "{\"text\":\"\",\"extra\":[{\"text\":\"Damage: \",\"color\":\"gray\"},{\"text\":\"+150\",\"color\":\"red\"}]}",
    "{\"text\":\"\",\"extra\":[{\"text\":\"Strength: \",\"color\":\"gray\"},{\"text\":\"+80\",\"color\":\"red\"}]}",
    "{\"text\":\"\",\"extra\":[{\"text\":\"Intelligence: \",\"color\":\"gray\"},{\"text\":\"+100\",\"color\":\"green\"}]}",
    "{\"text\":\"\",\"extra\":[{\"text\":\" \"},{\"text\":\"[\",\"color\":\"dark_gray\"},{\"text\":\"✎\",\"color\":\"gray\"},{\"text\":\"] [❤]\",\"color\":\"dark_gray\"}]}",
    "{\"text\":\"\"}",
    "{\"text\":\"\",\"extra\":[{\"text\":\"Ability: Instant Heal \",\"color\":\"gold\"},{\"text\":\"RIGHT CLICK\",\"color\":\"yellow\",\"bold\":true}]}",
    "{\"text\":\"\",\"extra\":[{\"text\":\"Heal for \",\"color\":\"gray\"},{\"text\":\"168 \",\"color\":\"red\"},{\"text\":\"+ \",\"color\":\"gray\"},{\"text\":\"5%❤ \",\"color\":\"red\"},{\"text\":\"and heal players within \",\"color\":\"gray\"},{\"text\":\"8\",\"color\":\"green\"}]}",
    "{\"text\":\"\",\"extra\":[{\"text\":\"blocks for \",\"color\":\"gray\"},{\"text\":\"56❤\",\"color\":\"red\"},{\"text\":\".\",\"color\":\"gray\"}]}",
    "{\"text\":\"\",\"extra\":[{\"text\":\"Mana Cost: \",\"color\":\"dark_gray\"},{\"text\":\"70\",\"color\":\"dark_aqua\"}]}",
    "{\"text\":\"\",\"extra\":[{\"text\":\"Charges: \",\"color\":\"dark_gray\"},{\"text\":\"5 \",\"color\":\"yellow\"},{\"text\":\"/ \",\"color\":\"dark_gray\"},{\"text\":\"15s\",\"color\":\"green\"}]}",
    "{\"text\":\"\"}",
    "{\"text\":\"\",\"extra\":[{\"text\":\"Gain \",\"color\":\"gray\"},{\"text\":\"+2 \",\"color\":\"green\"},{\"text\":\"extra max charges when you\",\"color\":\"gray\"}]}",
    "{\"text\":\"\",\"extra\":[{\"text\":\"play as a \",\"color\":\"gray\"},{\"text\":\"Healer \",\"color\":\"green\"},{\"text\":\"in Dungeons.\",\"color\":\"gray\"}]}",
    "{\"text\":\"\"}",
    "{\"text\":\"This item can be reforged!\",\"color\":\"dark_gray\"}",
    "{\"text\":\"LEGENDARY SWORD\",\"color\":\"gold\",\"bold\":true}"
  ],
  "internalname": "FLORID_ZOMBIE_SWORD",
  "clickcommand": "viewrecipe",
  "crafttext": "",
  "modver": "Firmament 3.2.0-dev+mc1.21.5+g0b9d5bd",
  "infoType": "WIKI_URL",
  "info": [
    "https://hypixel-skyblock.fandom.com/wiki/Florid_Zombie_Sword",
    "https://wiki.hypixel.net/Florid_Zombie_Sword"
  ],
  "recipe": {
    "A1": "",
    "A2": "HEALING_TISSUE:12",
    "A3": "",
    "B1": "",
    "B2": "HEALING_TISSUE:12",
    "B3": "",
    "C1": "",
    "C2": "ORNATE_ZOMBIE_SWORD:1",
    "C3": ""
  },
  "format_version": 1,
  "conversion_method": "modern_1215_components",
  "converted_modern": true
}