{
  "itemid": "minecraft:player_head",
  "displayname": "{\"text\":\"Fruit Bowl\",\"color\":\"blue\"}",
  "nbttag": "{\"id\":\"minecraft:player_head\",\"count\":1,\"components\":{\"minecraft:custom_name\":\"{\\\"text\\\":\\\"Fruit Bowl\\\",\\\"color\\\":\\\"blue\\\"}\",\"minecraft:lore\":[\"{\\\"text\\\":\\\"Click on a player while holding this\\\",\\\"color\\\":\\\"gray\\\"}\",\"{\\\"text\\\":\\\"item to add the name of their profile\\\",\\\"color\\\":\\\"gray\\\"}\",\"{\\\"text\\\":\\\"to this item.\\\",\\\"color\\\":\\\"gray\\\"}\",\"{\\\"text\\\":\\\"\\\"}\",\"{\\\"text\\\":\\\"Find one of each default profile\\\",\\\"color\\\":\\\"gray\\\"}\",\"{\\\"text\\\":\\\"name to reset this item and\\\",\\\"color\\\":\\\"gray\\\"}\",\"{\\\"text\\\":\\\"\\\",\\\"extra\\\":[{\\\"text\\\":\\\"permanently gain \\\",\\\"color\\\":\\\"gray\\\"},{\\\"text\\\":\\\"+1☯ Farming\\\",\\\"color\\\":\\\"dark_aqua\\\"}]}\",\"{\\\"text\\\":\\\"\\\",\\\"extra\\\":[{\\\"text\\\":\\\"Wisdom \\\",\\\"color\\\":\\\"dark_aqua\\\"},{\\\"text\\\":\\\"and \\\",\\\"color\\\":\\\"gray\\\"},{\\\"text\\\":\\\"250,000 Coins\\\",\\\"color\\\":\\\"gold\\\"},{\\\"text\\\":\\\".\\\",\\\"color\\\":\\\"gray\\\"}]}\",\"{\\\"text\\\":\\\"\\\"}\",\"{\\\"text\\\":\\\"Names missing:\\\",\\\"color\\\":\\\"gray\\\"}\",\"{\\\"text\\\":\\\"\\\",\\\"extra\\\":[{\\\"text\\\":\\\"Apple\\\",\\\"color\\\":\\\"aqua\\\"},{\\\"text\\\":\\\", \\\",\\\"color\\\":\\\"gray\\\"},{\\\"text\\\":\\\"Banana\\\",\\\"color\\\":\\\"aqua\\\"},{\\\"text\\\":\\\", \\\",\\\"color\\\":\\\"gray\\\"},{\\\"text\\\":\\\"Blueberry\\\",\\\"color\\\":\\\"aqua\\\"},{\\\"text\\\":\\\", \\\",\\\"color\\\":\\\"gray\\\"},{\\\"text\\\":\\\"Cucumber\\\",\\\"color\\\":\\\"aqua\\\"},{\\\"text\\\":\\\", \\\",\\\"color\\\":\\\"gray\\\"},{\\\"text\\\":\\\"Coconut\\\",\\\"color\\\":\\\"aqua\\\"},{\\\"text\\\":\\\",\\\",\\\"color\\\":\\\"gray\\\"}]}\",\"{\\\"text\\\":\\\"\\\",\\\"extra\\\":[{\\\"text\\\":\\\"Grapes\\\",\\\"color\\\":\\\"aqua\\\"},{\\\"text\\\":\\\", \\\",\\\"color\\\":\\\"gray\\\"},{\\\"text\\\":\\\"Kiwi\\\",\\\"color\\\":\\\"aqua\\\"},{\\\"text\\\":\\\", \\\",\\\"color\\\":\\\"gray\\\"},{\\\"text\\\":\\\"Lemon\\\",\\\"color\\\":\\\"aqua\\\"},{\\\"text\\\":\\\", \\\",\\\"color\\\":\\\"gray\\\"},{\\\"text\\\":\\\"Lime\\\",\\\"color\\\":\\\"aqua\\\"},{\\\"text\\\":\\\", \\\",\\\"color\\\":\\\"gray\\\"},{\\\"text\\\":\\\"Mango\\\",\\\"color\\\":\\\"aqua\\\"},{\\\"text\\\":\\\", \\\",\\\"color\\\":\\\"gray\\\"},{\\\"text\\\":\\\"Orange\\\",\\\"color\\\":\\\"aqua\\\"},{\\\"text\\\":\\\",\\\",\\\"color\\\":\\\"gray\\\"}]}\",\"{\\\"text\\\":\\\"\\\",\\\"extra\\\":[{\\\"text\\\":\\\"Papaya\\\",\\\"color\\\":\\\"aqua\\\"},{\\\"text\\\":\\\", \\\",\\\"color\\\":\\\"gray\\\"},{\\\"text\\\":\\\"Pineapple\\\",\\\"color\\\":\\\"aqua\\\"},{\\\"text\\\":\\\", \\\",\\\"color\\\":\\\"gray\\\"},{\\\"text\\\":\\\"Peach\\\",\\\"color\\\":\\\"aqua\\\"},{\\\"text\\\":\\\", \\\",\\\"color\\\":\\\"gray\\\"},{\\\"text\\\":\\\"Pear\\\",\\\"color\\\":\\\"aqua\\\"},{\\\"text\\\":\\\", \\\",\\\"color\\\":\\\"gray\\\"},{\\\"text\\\":\\\"Pomegranate\\\",\\\"color\\\":\\\"aqua\\\"},{\\\"text\\\":\\\",\\\",\\\"color\\\":\\\"gray\\\"}]}\",\"{\\\"text\\\":\\\"\\\",\\\"extra\\\":[{\\\"text\\\":\\\"Raspberry\\\",\\\"color\\\":\\\"aqua\\\"},{\\\"text\\\":\\\", \\\",\\\"color\\\":\\\"gray\\\"},{\\\"text\\\":\\\"Strawberry\\\",\\\"color\\\":\\\"aqua\\\"},{\\\"text\\\":\\\", \\\",\\\"color\\\":\\\"gray\\\"},{\\\"text\\\":\\\"Tomato\\\",\\\"color\\\":\\\"aqua\\\"},{\\\"text\\\":\\\", \\\",\\\"color\\\":\\\"gray\\\"},{\\\"text\\\":\\\"Watermelon\\\",\\\"color\\\":\\\"aqua\\\"},{\\\"text\\\":\\\",\\\",\\\"color\\\":\\\"gray\\\"}]}\",\"{\\\"text\\\":\\\"Zucchini\\\",\\\"color\\\":\\\"aqua\\\"}\",\"{\\\"text\\\":\\\"\\\"}\",\"{\\\"text\\\":\\\"You may only gain the bonus once!\\\",\\\"color\\\":\\\"dark_gray\\\"}\",\"{\\\"text\\\":\\\"\\\"}\",\"{\\\"text\\\":\\\"RARE\\\",\\\"color\\\":\\\"blue\\\",\\\"bold\\\":true}\"]}}",
  "damage": 0,
  "lore": [
    "{\"text\":\"Click on a player while holding this\",\"color\":\"gray\"}",
    "{\"text\":\"item to add the name of their profile\",\"color\":\"gray\"}",
    "{\"text\":\"to this item.\",\"color\":\"gray\"}",
    "{\"text\":\"\"}",
    "{\"text\":\"Find one of each default profile\",\"color\":\"gray\"}",
    "{\"text\":\"name to reset this item and\",\"color\":\"gray\"}",
    "{\"text\":\"\",\"extra\":[{\"text\":\"permanently gain \",\"color\":\"gray\"},{\"text\":\"+1☯ Farming\",\"color\":\"dark_aqua\"}]}",
    "{\"text\":\"\",\"extra\":[{\"text\":\"Wisdom \",\"color\":\"dark_aqua\"},{\"text\":\"and \",\"color\":\"gray\"},{\"text\":\"250,000 Coins\",\"color\":\"gold\"},{\"text\":\".\",\"color\":\"gray\"}]}",
    "{\"text\":\"\"}",
    "{\"text\":\"Names missing:\",\"color\":\"gray\"}",
    "{\"text\":\"\",\"extra\":[{\"text\":\"Apple\",\"color\":\"aqua\"},{\"text\":\", \",\"color\":\"gray\"},{\"text\":\"Banana\",\"color\":\"aqua\"},{\"text\":\", \",\"color\":\"gray\"},{\"text\":\"Blueberry\",\"color\":\"aqua\"},{\"text\":\", \",\"color\":\"gray\"},{\"text\":\"Cucumber\",\"color\":\"aqua\"},{\"text\":\", \",\"color\":\"gray\"},{\"text\":\"Coconut\",\"color\":\"aqua\"},{\"text\":\",\",\"color\":\"gray\"}]}",
    "{\"text\":\"\",\"extra\":[{\"text\":\"Grapes\",\"color\":\"aqua\"},{\"text\":\", \",\"color\":\"gray\"},{\"text\":\"Kiwi\",\"color\":\"aqua\"},{\"text\":\", \",\"color\":\"gray\"},{\"text\":\"Lemon\",\"color\":\"aqua\"},{\"text\":\", \",\"color\":\"gray\"},{\"text\":\"Lime\",\"color\":\"aqua\"},{\"text\":\", \",\"color\":\"gray\"},{\"text\":\"Mango\",\"color\":\"aqua\"},{\"text\":\", \",\"color\":\"gray\"},{\"text\":\"Orange\",\"color\":\"aqua\"},{\"text\":\",\",\"color\":\"gray\"}]}",
    "{\"text\":\"\",\"extra\":[{\"text\":\"Papaya\",\"color\":\"aqua\"},{\"text\":\", \",\"color\":\"gray\"},{\"text\":\"Pineapple\",\"color\":\"aqua\"},{\"text\":\", \",\"color\":\"gray\"},{\"text\":\"Peach\",\"color\":\"aqua\"},{\"text\":\", \",\"color\":\"gray\"},{\"text\":\"Pear\",\"color\":\"aqua\"},{\"text\":\", \",\"color\":\"gray\"},{\"text\":\"Pomegranate\",\"color\":\"aqua\"},{\"text\":\",\",\"color\":\"gray\"}]}",
    "{\"text\":\"\",\"extra\":[{\"text\":\"Raspberry\",\"color\":\"aqua\"},{\"text\":\", \",\"color\":\"gray\"},{\"text\":\"Strawberry\",\"color\":\"aqua\"},{\"text\":\", \",\"color\":\"gray\"},{\"text\":\"Tomato\",\"color\":\"aqua\"},{\"text\":\", \",\"color\":\"gray\"},{\"text\":\"Watermelon\",\"color\":\"aqua\"},{\"text\":\",\",\"color\":\"gray\"}]}",
    "{\"text\":\"Zucchini\",\"color\":\"aqua\"}",
    "{\"text\":\"\"}",
    "{\"text\":\"You may only gain the bonus once!\",\"color\":\"dark_gray\"}",
    "{\"text\":\"\"}",
    "{\"text\":\"RARE\",\"color\":\"blue\",\"bold\":true}"
  ],
  "internalname": "FRUIT_BOWL",
  "clickcommand": "",
  "crafttext": "",
  "modver": "Firmament 3.2.0-dev+mc1.21.5+g64ef955",
  "infoType": "WIKI_URL",
  "info": [
    "https://hypixel-skyblock.fandom.com/wiki/Fruit_Bowl",
    "https://wiki.hypixel.net/Fruit_Bowl"
  ],
  "format_version": 1,
  "conversion_method": "modern_1215_components",
  "converted_modern": true
}