{
  "itemid": "minecraft:player_head",
  "displayname": "{\"text\":\"\",\"extra\":[{\"text\":\"[Lvl {LVL}] \",\"color\":\"gray\"},{\"text\":\"Golem\",\"color\":\"dark_purple\"}]}",
  "nbttag": "{\"id\":\"minecraft:player_head\",\"count\":1,\"components\":{\"minecraft:custom_name\":\"{\\\"text\\\":\\\"\\\",\\\"extra\\\":[{\\\"text\\\":\\\"[Lvl {LVL}] \\\",\\\"color\\\":\\\"gray\\\"},{\\\"text\\\":\\\"Golem\\\",\\\"color\\\":\\\"dark_purple\\\"}]}\",\"minecraft:lore\":[\"{\\\"text\\\":\\\"Combat Pet\\\",\\\"color\\\":\\\"dark_gray\\\"}\",\"{\\\"text\\\":\\\"\\\"}\",\"{\\\"text\\\":\\\"\\\",\\\"extra\\\":[{\\\"text\\\":\\\"Health: \\\",\\\"color\\\":\\\"gray\\\"},{\\\"text\\\":\\\"{HEALTH}\\\",\\\"color\\\":\\\"green\\\"}]}\",\"{\\\"text\\\":\\\"\\\",\\\"extra\\\":[{\\\"text\\\":\\\"Strength: \\\",\\\"color\\\":\\\"gray\\\"},{\\\"text\\\":\\\"{STRENGTH}\\\",\\\"color\\\":\\\"red\\\"}]}\",\"{\\\"text\\\":\\\"\\\",\\\"extra\\\":[{\\\"text\\\":\\\"Swing Range: \\\",\\\"color\\\":\\\"gray\\\"},{\\\"text\\\":\\\"{SWING_RANGE}\\\",\\\"color\\\":\\\"green\\\"}]}\",\"{\\\"text\\\":\\\"\\\"}\",\"{\\\"text\\\":\\\"Last Stand\\\",\\\"color\\\":\\\"gold\\\"}\",\"{\\\"text\\\":\\\"\\\",\\\"extra\\\":[{\\\"text\\\":\\\"While at less than \\\",\\\"color\\\":\\\"gray\\\"},{\\\"text\\\":\\\"20% HP\\\",\\\"color\\\":\\\"green\\\"},{\\\"text\\\":\\\", reduce\\\",\\\"color\\\":\\\"gray\\\"}]}\",\"{\\\"text\\\":\\\"\\\",\\\"extra\\\":[{\\\"text\\\":\\\"incoming damage by \\\",\\\"color\\\":\\\"gray\\\"},{\\\"text\\\":\\\"20%\\\",\\\"color\\\":\\\"green\\\"},{\\\"text\\\":\\\". Additionally,\\\",\\\"color\\\":\\\"gray\\\"}]}\",\"{\\\"text\\\":\\\"\\\",\\\"extra\\\":[{\\\"text\\\":\\\"gain a temporary shield equal to \\\",\\\"color\\\":\\\"gray\\\"},{\\\"text\\\":\\\"40%\\\",\\\"color\\\":\\\"green\\\"}]}\",\"{\\\"text\\\":\\\"\\\",\\\"extra\\\":[{\\\"text\\\":\\\"of your maximum health and deal \\\",\\\"color\\\":\\\"gray\\\"},{\\\"text\\\":\\\"40%\\\",\\\"color\\\":\\\"green\\\"}]}\",\"{\\\"text\\\":\\\"more damage.\\\",\\\"color\\\":\\\"gray\\\"}\",\"{\\\"text\\\":\\\"(Lasts 12s, 60s cooldown)\\\",\\\"color\\\":\\\"dark_gray\\\"}\",\"{\\\"text\\\":\\\"\\\"}\",\"{\\\"text\\\":\\\"Ricochet\\\",\\\"color\\\":\\\"gold\\\"}\",\"{\\\"text\\\":\\\"\\\",\\\"extra\\\":[{\\\"text\\\":\\\"Your iron plating causes \\\",\\\"color\\\":\\\"gray\\\"},{\\\"text\\\":\\\"{0}% \\\",\\\"color\\\":\\\"green\\\"},{\\\"text\\\":\\\"of\\\",\\\"color\\\":\\\"gray\\\"}]}\",\"{\\\"text\\\":\\\"attacks to ricochet and hit the\\\",\\\"color\\\":\\\"gray\\\"}\",\"{\\\"text\\\":\\\"attacker.\\\",\\\"color\\\":\\\"gray\\\"}\",\"{\\\"text\\\":\\\"\\\"}\",\"{\\\"text\\\":\\\"Right-click to add this pet to your\\\",\\\"color\\\":\\\"yellow\\\"}\",\"{\\\"text\\\":\\\"pet menu!\\\",\\\"color\\\":\\\"yellow\\\"}\",\"{\\\"text\\\":\\\"\\\"}\",\"{\\\"text\\\":\\\"EPIC\\\",\\\"color\\\":\\\"dark_purple\\\",\\\"bold\\\":true}\"]}}",
  "damage": 0,
  "lore": [
    "{\"text\":\"Combat Pet\",\"color\":\"dark_gray\"}",
    "{\"text\":\"\"}",
    "{\"text\":\"\",\"extra\":[{\"text\":\"Health: \",\"color\":\"gray\"},{\"text\":\"{HEALTH}\",\"color\":\"green\"}]}",
    "{\"text\":\"\",\"extra\":[{\"text\":\"Strength: \",\"color\":\"gray\"},{\"text\":\"{STRENGTH}\",\"color\":\"red\"}]}",
    "{\"text\":\"\",\"extra\":[{\"text\":\"Swing Range: \",\"color\":\"gray\"},{\"text\":\"{SWING_RANGE}\",\"color\":\"green\"}]}",
    "{\"text\":\"\"}",
    "{\"text\":\"Last Stand\",\"color\":\"gold\"}",
    "{\"text\":\"\",\"extra\":[{\"text\":\"While at less than \",\"color\":\"gray\"},{\"text\":\"20% HP\",\"color\":\"green\"},{\"text\":\", reduce\",\"color\":\"gray\"}]}",
    "{\"text\":\"\",\"extra\":[{\"text\":\"incoming damage by \",\"color\":\"gray\"},{\"text\":\"20%\",\"color\":\"green\"},{\"text\":\". Additionally,\",\"color\":\"gray\"}]}",
    "{\"text\":\"\",\"extra\":[{\"text\":\"gain a temporary shield equal to \",\"color\":\"gray\"},{\"text\":\"40%\",\"color\":\"green\"}]}",
    "{\"text\":\"\",\"extra\":[{\"text\":\"of your maximum health and deal \",\"color\":\"gray\"},{\"text\":\"40%\",\"color\":\"green\"}]}",
    "{\"text\":\"more damage.\",\"color\":\"gray\"}",
    "{\"text\":\"(Lasts 12s, 60s cooldown)\",\"color\":\"dark_gray\"}",
    "{\"text\":\"\"}",
    "{\"text\":\"Ricochet\",\"color\":\"gold\"}",
    "{\"text\":\"\",\"extra\":[{\"text\":\"Your iron plating causes \",\"color\":\"gray\"},{\"text\":\"{0}% \",\"color\":\"green\"},{\"text\":\"of\",\"color\":\"gray\"}]}",
    "{\"text\":\"attacks to ricochet and hit the\",\"color\":\"gray\"}",
    "{\"text\":\"attacker.\",\"color\":\"gray\"}",
    "{\"text\":\"\"}",
    "{\"text\":\"Right-click to add this pet to your\",\"color\":\"yellow\"}",
    "{\"text\":\"pet menu!\",\"color\":\"yellow\"}",
    "{\"text\":\"\"}",
    "{\"text\":\"EPIC\",\"color\":\"dark_purple\",\"bold\":true}"
  ],
  "internalname": "GOLEM;3",
  "clickcommand": "",
  "modver": "2.4.0",
  "infoType": "WIKI_URL",
  "info": [
    "https://hypixel-skyblock.fandom.com/wiki/Golem_Pet",
    "https://wiki.hypixel.net/Golem_Pet"
  ],
  "crafttext": "",
  "format_version": 1,
  "conversion_method": "modern_1215_components",
  "converted_modern": true
}