{
  "itemid": "minecraft:player_head",
  "displayname": "{\"text\":\"Green Jerry Talisman\",\"color\":\"green\"}",
  "nbttag": "{\"id\":\"minecraft:player_head\",\"count\":1,\"components\":{\"minecraft:custom_name\":\"{\\\"text\\\":\\\"Green Jerry Talisman\\\",\\\"color\\\":\\\"green\\\"}\",\"minecraft:lore\":[\"{\\\"text\\\":\\\"\\\",\\\"extra\\\":[{\\\"text\\\":\\\"Intelligence: \\\",\\\"color\\\":\\\"gray\\\"},{\\\"text\\\":\\\"-1\\\",\\\"color\\\":\\\"green\\\"}]}\",\"{\\\"text\\\":\\\"\\\"}\",\"{\\\"text\\\":\\\"Wear to prove you love Jerry,\\\",\\\"color\\\":\\\"gray\\\"}\",\"{\\\"text\\\":\\\"or wear to prove you hate\\\",\\\"color\\\":\\\"gray\\\"}\",\"{\\\"text\\\":\\\"Jerry.\\\",\\\"color\\\":\\\"gray\\\"}\",\"{\\\"text\\\":\\\"\\\"}\",\"{\\\"text\\\":\\\"Right-click to view recipes!\\\",\\\"color\\\":\\\"yellow\\\"}\",\"{\\\"text\\\":\\\"\\\"}\",\"{\\\"text\\\":\\\"UNCOMMON ACCESSORY\\\",\\\"color\\\":\\\"green\\\",\\\"bold\\\":true}\"]}}",
  "damage": 0,
  "lore": [
    "{\"text\":\"\",\"extra\":[{\"text\":\"Intelligence: \",\"color\":\"gray\"},{\"text\":\"-1\",\"color\":\"green\"}]}",
    "{\"text\":\"\"}",
    "{\"text\":\"Wear to prove you love Jerry,\",\"color\":\"gray\"}",
    "{\"text\":\"or wear to prove you hate\",\"color\":\"gray\"}",
    "{\"text\":\"Jerry.\",\"color\":\"gray\"}",
    "{\"text\":\"\"}",
    "{\"text\":\"Right-click to view recipes!\",\"color\":\"yellow\"}",
    "{\"text\":\"\"}",
    "{\"text\":\"UNCOMMON ACCESSORY\",\"color\":\"green\",\"bold\":true}"
  ],
  "internalname": "JERRY_TALISMAN_GREEN",
  "clickcommand": "",
  "crafttext": "",
  "modver": "Firmament 3.2.0-dev+mc1.21.5+g64ef955",
  "infoType": "WIKI_URL",
  "info": [
    "https://hypixel-skyblock.fandom.com/wiki/Green_Jerry_Talisman",
    "https://wiki.hypixel.net/Green_Jerry_Talisman"
  ],
  "format_version": 1,
  "conversion_method": "modern_1215_components",
  "converted_modern": true
}