{
  "itemid": "minecraft:player_head",
  "displayname": "{\"text\":\"Lesser Orb of Healing\",\"color\":\"dark_purple\"}",
  "nbttag": "{\"id\":\"minecraft:player_head\",\"count\":1,\"components\":{\"minecraft:custom_name\":\"{\\\"text\\\":\\\"Lesser Orb of Healing\\\",\\\"color\\\":\\\"dark_purple\\\"}\",\"minecraft:lore\":[\"{\\\"text\\\":\\\"A shard of a Dungeon Blessing,\\\",\\\"color\\\":\\\"gray\\\"}\",\"{\\\"text\\\":\\\"capable of being bestowed upon\\\",\\\"color\\\":\\\"gray\\\"}\",\"{\\\"text\\\":\\\"another player for a continuous buff,\\\",\\\"color\\\":\\\"gray\\\"}\",\"{\\\"text\\\":\\\"but draining mana.\\\",\\\"color\\\":\\\"gray\\\"}\",\"{\\\"text\\\":\\\"\\\"}\",\"{\\\"text\\\":\\\"\\\",\\\"extra\\\":[{\\\"text\\\":\\\"Orb of Life \\\",\\\"color\\\":\\\"green\\\"},{\\\"text\\\":\\\"RIGHT CLICK TEAMMATE\\\",\\\"color\\\":\\\"yellow\\\",\\\"bold\\\":true}]}\",\"{\\\"text\\\":\\\"\\\",\\\"extra\\\":[{\\\"text\\\":\\\"Heals \\\",\\\"color\\\":\\\"gray\\\"},{\\\"text\\\":\\\"5%\\\",\\\"color\\\":\\\"red\\\"},{\\\"text\\\":\\\" of max \\\",\\\"color\\\":\\\"gray\\\"},{\\\"text\\\":\\\"❤ \\\",\\\"color\\\":\\\"red\\\"},{\\\"text\\\":\\\"per second.\\\",\\\"color\\\":\\\"gray\\\"}]}\",\"{\\\"text\\\":\\\"Ignores ♨ Vitality!\\\",\\\"color\\\":\\\"dark_gray\\\"}\",\"{\\\"text\\\":\\\"\\\",\\\"extra\\\":[{\\\"text\\\":\\\"Mana Drain: \\\",\\\"color\\\":\\\"dark_gray\\\"},{\\\"text\\\":\\\"50 per second\\\",\\\"color\\\":\\\"dark_aqua\\\"}]}\",\"{\\\"text\\\":\\\"\\\"}\",\"{\\\"text\\\":\\\"\\\",\\\"extra\\\":[{\\\"text\\\":\\\"❣ \\\",\\\"color\\\":\\\"dark_red\\\"},{\\\"text\\\":\\\"Requires Catacombs Skill 16.\\\",\\\"color\\\":\\\"red\\\"}]}\",\"{\\\"text\\\":\\\"EPIC DUNGEON ITEM\\\",\\\"color\\\":\\\"dark_purple\\\",\\\"bold\\\":true}\"]}}",
  "damage": 0,
  "lore": [
    "{\"text\":\"A shard of a Dungeon Blessing,\",\"color\":\"gray\"}",
    "{\"text\":\"capable of being bestowed upon\",\"color\":\"gray\"}",
    "{\"text\":\"another player for a continuous buff,\",\"color\":\"gray\"}",
    "{\"text\":\"but draining mana.\",\"color\":\"gray\"}",
    "{\"text\":\"\"}",
    "{\"text\":\"\",\"extra\":[{\"text\":\"Orb of Life \",\"color\":\"green\"},{\"text\":\"RIGHT CLICK TEAMMATE\",\"color\":\"yellow\",\"bold\":true}]}",
    "{\"text\":\"\",\"extra\":[{\"text\":\"Heals \",\"color\":\"gray\"},{\"text\":\"5%\",\"color\":\"red\"},{\"text\":\" of max \",\"color\":\"gray\"},{\"text\":\"❤ \",\"color\":\"red\"},{\"text\":\"per second.\",\"color\":\"gray\"}]}",
    "{\"text\":\"Ignores ♨ Vitality!\",\"color\":\"dark_gray\"}",
    "{\"text\":\"\",\"extra\":[{\"text\":\"Mana Drain: \",\"color\":\"dark_gray\"},{\"text\":\"50 per second\",\"color\":\"dark_aqua\"}]}",
    "{\"text\":\"\"}",
    "{\"text\":\"\",\"extra\":[{\"text\":\"❣ \",\"color\":\"dark_red\"},{\"text\":\"Requires Catacombs Skill 16.\",\"color\":\"red\"}]}",
    "{\"text\":\"EPIC DUNGEON ITEM\",\"color\":\"dark_purple\",\"bold\":true}"
  ],
  "internalname": "LESSER_ORB_OF_HEALING",
  "clickcommand": "viewrecipe",
  "crafttext": "",
  "modver": "Firmament 3.2.0-dev+mc1.21.5+g0b9d5bd",
  "infoType": "WIKI_URL",
  "info": [
    "https://hypixel-skyblock.fandom.com/wiki/Lesser_Orb_of_Healing",
    "https://wiki.hypixel.net/Lesser_Orb_Of_Healing"
  ],
  "recipe": {
    "A1": "MIMIC_FRAGMENT:1",
    "A2": "MIMIC_FRAGMENT:1",
    "A3": "MIMIC_FRAGMENT:1",
    "B1": "MIMIC_FRAGMENT:1",
    "B2": "MIMIC_FRAGMENT:1",
    "B3": "MIMIC_FRAGMENT:1",
    "C1": "MIMIC_FRAGMENT:1",
    "C2": "MIMIC_FRAGMENT:1",
    "C3": "MIMIC_FRAGMENT:1"
  },
  "format_version": 1,
  "conversion_method": "modern_1215_components",
  "converted_modern": true
}