{
  "itemid": "minecraft:player_head",
  "displayname": "{\"text\":\"Porc (NPC)\",\"color\":\"blue\"}",
  "nbttag": "{\"id\":\"minecraft:player_head\",\"count\":1,\"components\":{\"minecraft:custom_name\":\"{\\\"text\\\":\\\"Porc (NPC)\\\",\\\"color\\\":\\\"blue\\\"}\",\"minecraft:lore\":[\"{\\\"text\\\":\\\"\\\"}\"],\"minecraft:custom_data\":{\"id\":\"PORC_NPC\"}}}",
  "damage": 0,
  "lore": [
    "{\"text\":\"\"}"
  ],
  "internalname": "PORC_NPC",
  "clickcommand": "",
  "modver": "2.1.1-PRE",
  "x": -577,
  "y": 119,
  "z": -857,
  "island": "crimson_isle",
  "infoType": "WIKI_URL",
  "info": [
    "https://hypixel-skyblock.fandom.com/wiki/Porc",
    "https://wiki.hypixel.net/Porc"
  ],
  "format_version": 1,
  "conversion_method": "modern_1215_components",
  "converted_modern": true
}