{
  "itemid": "minecraft:player_head",
  "displayname": "{\"text\":\"\",\"extra\":[{\"text\":\"[Lvl {LVL}] \",\"color\":\"gray\"},{\"text\":\"Scatha\",\"color\":\"gold\"}]}",
  "nbttag": "{\"id\":\"minecraft:player_head\",\"count\":1,\"components\":{\"minecraft:custom_name\":\"{\\\"text\\\":\\\"\\\",\\\"extra\\\":[{\\\"text\\\":\\\"[Lvl {LVL}] \\\",\\\"color\\\":\\\"gray\\\"},{\\\"text\\\":\\\"Scatha\\\",\\\"color\\\":\\\"gold\\\"}]}\",\"minecraft:lore\":[\"{\\\"text\\\":\\\"Mining Pet\\\",\\\"color\\\":\\\"dark_gray\\\"}\",\"{\\\"text\\\":\\\"\\\"}\",\"{\\\"text\\\":\\\"\\\",\\\"extra\\\":[{\\\"text\\\":\\\"Mining Speed: \\\",\\\"color\\\":\\\"gray\\\"},{\\\"text\\\":\\\"{MINING_SPEED}\\\",\\\"color\\\":\\\"green\\\"}]}\",\"{\\\"text\\\":\\\"\\\",\\\"extra\\\":[{\\\"text\\\":\\\"Mining Fortune: \\\",\\\"color\\\":\\\"gray\\\"},{\\\"text\\\":\\\"{MINING_FORTUNE}\\\",\\\"color\\\":\\\"green\\\"}]}\",\"{\\\"text\\\":\\\"\\\"}\",\"{\\\"text\\\":\\\"Burrowing\\\",\\\"color\\\":\\\"gold\\\"}\",\"{\\\"text\\\":\\\"\\\",\\\"extra\\\":[{\\\"text\\\":\\\"Grants a \\\",\\\"color\\\":\\\"gray\\\"},{\\\"text\\\":\\\"+{0}% \\\",\\\"color\\\":\\\"green\\\"},{\\\"text\\\":\\\"chance to find\\\",\\\"color\\\":\\\"gray\\\"}]}\",\"{\\\"text\\\":\\\"\\\",\\\"extra\\\":[{\\\"text\\\":\\\"Treasure Chests \\\",\\\"color\\\":\\\"yellow\\\"},{\\\"text\\\":\\\"while mining.\\\",\\\"color\\\":\\\"gray\\\"}]}\",\"{\\\"text\\\":\\\"\\\"}\",\"{\\\"text\\\":\\\"Drill Infusion\\\",\\\"color\\\":\\\"gold\\\"}\",\"{\\\"text\\\":\\\"\\\",\\\"extra\\\":[{\\\"text\\\":\\\"Grants \\\",\\\"color\\\":\\\"gray\\\"},{\\\"text\\\":\\\"+{1}☘ Gemstone Fortune \\\",\\\"color\\\":\\\"gold\\\"},{\\\"text\\\":\\\"to\\\",\\\"color\\\":\\\"gray\\\"}]}\",\"{\\\"text\\\":\\\"Drills.\\\",\\\"color\\\":\\\"gray\\\"}\",\"{\\\"text\\\":\\\"\\\"}\",\"{\\\"text\\\":\\\"Bejeweled Eyes\\\",\\\"color\\\":\\\"gold\\\"}\",\"{\\\"text\\\":\\\"\\\",\\\"extra\\\":[{\\\"text\\\":\\\"Earn \\\",\\\"color\\\":\\\"gray\\\"},{\\\"text\\\":\\\"+{2}% \\\",\\\"color\\\":\\\"green\\\"},{\\\"text\\\":\\\"Gemstone Powder \\\",\\\"color\\\":\\\"light_purple\\\"},{\\\"text\\\":\\\"from all\\\",\\\"color\\\":\\\"gray\\\"}]}\",\"{\\\"text\\\":\\\"sources.\\\",\\\"color\\\":\\\"gray\\\"}\",\"{\\\"text\\\":\\\"\\\"}\",\"{\\\"text\\\":\\\"Right-click to add this pet to your\\\",\\\"color\\\":\\\"yellow\\\"}\",\"{\\\"text\\\":\\\"pet menu!\\\",\\\"color\\\":\\\"yellow\\\"}\",\"{\\\"text\\\":\\\"\\\"}\",\"{\\\"text\\\":\\\"LEGENDARY\\\",\\\"color\\\":\\\"gold\\\",\\\"bold\\\":true}\"],\"minecraft:custom_data\":{\"\\\\\\\"candyUsed\\\\\\\"\":0,\"\\\\\\\"hideRightClick\\\\\\\"\":\"false\",\"\\\\\\\"exp\\\\\\\"\":0,\"petInfo\":\"{\\\\\\\"type\\\\\\\":\\\\\\\"SCATHA\\\\\",\"\\\\\\\"active\\\\\\\"\":\"false\",\"\\\\\\\"hideInfo\\\\\\\"\":\"false\",\"\\\\\\\"noMove\\\\\\\"\":\"false\",\"\\\\\\\"tier\\\\\\\"\":\"\\\\\\\"LEGENDARY\\\\\\\"\",\"\\\\\\\"uniqueId\\\\\\\"\":\"\\\\\\\"38ee8c0c-1af9-4ff2-bf87-4361569b834f\\\\\\\"\",\"\\\\\\\"uuid\\\\\\\"\":\"\\\\\\\"b622bf32-98e3-430a-924a-e026d5e29a66\\\\\\\"\"},\"minecraft:hide_additional_tooltip\":{}}}",
  "damage": 0,
  "lore": [
    "{\"text\":\"Mining Pet\",\"color\":\"dark_gray\"}",
    "{\"text\":\"\"}",
    "{\"text\":\"\",\"extra\":[{\"text\":\"Mining Speed: \",\"color\":\"gray\"},{\"text\":\"{MINING_SPEED}\",\"color\":\"green\"}]}",
    "{\"text\":\"\",\"extra\":[{\"text\":\"Mining Fortune: \",\"color\":\"gray\"},{\"text\":\"{MINING_FORTUNE}\",\"color\":\"green\"}]}",
    "{\"text\":\"\"}",
    "{\"text\":\"Burrowing\",\"color\":\"gold\"}",
    "{\"text\":\"\",\"extra\":[{\"text\":\"Grants a \",\"color\":\"gray\"},{\"text\":\"+{0}% \",\"color\":\"green\"},{\"text\":\"chance to find\",\"color\":\"gray\"}]}",
    "{\"text\":\"\",\"extra\":[{\"text\":\"Treasure Chests \",\"color\":\"yellow\"},{\"text\":\"while mining.\",\"color\":\"gray\"}]}",
    "{\"text\":\"\"}",
    "{\"text\":\"Drill Infusion\",\"color\":\"gold\"}",
    "{\"text\":\"\",\"extra\":[{\"text\":\"Grants \",\"color\":\"gray\"},{\"text\":\"+{1}☘ Gemstone Fortune \",\"color\":\"gold\"},{\"text\":\"to\",\"color\":\"gray\"}]}",
    "{\"text\":\"Drills.\",\"color\":\"gray\"}",
    "{\"text\":\"\"}",
    "{\"text\":\"Bejeweled Eyes\",\"color\":\"gold\"}",
    "{\"text\":\"\",\"extra\":[{\"text\":\"Earn \",\"color\":\"gray\"},{\"text\":\"+{2}% \",\"color\":\"green\"},{\"text\":\"Gemstone Powder \",\"color\":\"light_purple\"},{\"text\":\"from all\",\"color\":\"gray\"}]}",
    "{\"text\":\"sources.\",\"color\":\"gray\"}",
    "{\"text\":\"\"}",
    "{\"text\":\"Right-click to add this pet to your\",\"color\":\"yellow\"}",
    "{\"text\":\"pet menu!\",\"color\":\"yellow\"}",
    "{\"text\":\"\"}",
    "{\"text\":\"LEGENDARY\",\"color\":\"gold\",\"bold\":true}"
  ],
  "internalname": "SCATHA;4",
  "crafttext": "",
  "clickcommand": "",
  "modver": "",
  "infoType": "WIKI_URL",
  "info": [
    "https://hypixel-skyblock.fandom.com/wiki/Scatha_Pet",
    "https://wiki.hypixel.net/Scatha_Pet"
  ],
  "recipes": [
    {
      "type": "katgrade",
      "coins": 250000000,
      "time": 1209600,
      "input": "SCATHA;3",
      "output": "SCATHA;4",
      "items": [
        "ENCHANTED_HARD_STONE:256"
      ]
    }
  ],
  "format_version": 1,
  "conversion_method": "modern_1215_components",
  "converted_modern": true
}