{
  "itemid": "minecraft:iron_leggings",
  "displayname": "{\"text\":\"Silver Hunter Leggings\",\"color\":\"blue\"}",
  "nbttag": "{\"id\":\"minecraft:iron_leggings\",\"count\":1,\"components\":{\"minecraft:custom_name\":\"{\\\"text\\\":\\\"Silver Hunter Leggings\\\",\\\"color\\\":\\\"blue\\\"}\",\"minecraft:lore\":[\"{\\\"text\\\":\\\"\\\",\\\"extra\\\":[{\\\"text\\\":\\\"Health: \\\",\\\"color\\\":\\\"gray\\\"},{\\\"text\\\":\\\"+100\\\",\\\"color\\\":\\\"green\\\"}]}\",\"{\\\"text\\\":\\\"\\\",\\\"extra\\\":[{\\\"text\\\":\\\" \\\"},{\\\"text\\\":\\\"[☂]\\\",\\\"color\\\":\\\"dark_gray\\\"}]}\",\"{\\\"text\\\":\\\"\\\"}\",\"{\\\"text\\\":\\\"\\\",\\\"extra\\\":[{\\\"text\\\":\\\"Full Set Bonus: Peace Treaty \\\",\\\"color\\\":\\\"gold\\\"},{\\\"text\\\":\\\"(0/4)\\\",\\\"color\\\":\\\"gray\\\"}]}\",\"{\\\"text\\\":\\\"Gain immunity to Sea Creatures but\\\",\\\"color\\\":\\\"gray\\\"}\",\"{\\\"text\\\":\\\"they are immune to you and you can\\\",\\\"color\\\":\\\"gray\\\"}\",\"{\\\"text\\\":\\\"no longer catch them.\\\",\\\"color\\\":\\\"gray\\\"}\",\"{\\\"text\\\":\\\"\\\"}\",\"{\\\"text\\\":\\\"Tiered Bonus: Odger\u0027s Blessing (0/4)\\\",\\\"color\\\":\\\"dark_gray\\\"}\",\"{\\\"text\\\":\\\"\\\",\\\"extra\\\":[{\\\"text\\\":\\\"Grants \\\",\\\"color\\\":\\\"gray\\\"},{\\\"text\\\":\\\"+0♔ Trophy Fish Chance\\\",\\\"color\\\":\\\"gold\\\"},{\\\"text\\\":\\\".\\\",\\\"color\\\":\\\"gray\\\"}]}\",\"{\\\"text\\\":\\\" \\\"}\",\"{\\\"text\\\":\\\"\\\",\\\"extra\\\":[{\\\"text\\\":\\\"Full Set Bonus: Star Fisher \\\",\\\"color\\\":\\\"gold\\\"},{\\\"text\\\":\\\"(0/4)\\\",\\\"color\\\":\\\"gray\\\"}]}\",\"{\\\"text\\\":\\\"\\\",\\\"extra\\\":[{\\\"text\\\":\\\"Grants \\\",\\\"color\\\":\\\"gray\\\"},{\\\"text\\\":\\\"+0.4☂ Fishing Speed\\\",\\\"color\\\":\\\"aqua\\\"},{\\\"text\\\":\\\" per \\\",\\\"color\\\":\\\"gray\\\"},{\\\"text\\\":\\\"✪\\\",\\\"color\\\":\\\"gold\\\"}]}\",\"{\\\"text\\\":\\\"\\\",\\\"extra\\\":[{\\\"text\\\":\\\"Upgrade Star \\\",\\\"color\\\":\\\"gold\\\"},{\\\"text\\\":\\\"on your armor.\\\",\\\"color\\\":\\\"gray\\\"}]}\",\"{\\\"text\\\":\\\"\\\"}\",\"{\\\"text\\\":\\\"This item can be reforged!\\\",\\\"color\\\":\\\"dark_gray\\\"}\",\"{\\\"text\\\":\\\"\\\",\\\"extra\\\":[{\\\"text\\\":\\\"❣ \\\",\\\"color\\\":\\\"dark_red\\\"},{\\\"text\\\":\\\"Requires Adept Trophy Fisher.\\\",\\\"color\\\":\\\"red\\\"}]}\",\"{\\\"text\\\":\\\"\\\",\\\"extra\\\":[{\\\"text\\\":\\\"* \\\",\\\"color\\\":\\\"dark_gray\\\",\\\"bold\\\":true},{\\\"text\\\":\\\"Soulbound \\\",\\\"color\\\":\\\"dark_gray\\\"},{\\\"text\\\":\\\"**\\\",\\\"color\\\":\\\"dark_gray\\\",\\\"bold\\\":true}]}\",\"{\\\"text\\\":\\\"RARE LEGGINGS\\\",\\\"color\\\":\\\"blue\\\",\\\"bold\\\":true}\"],\"minecraft:custom_data\":{\"id\":\"SILVER_HUNTER_LEGGINGS\"},\"minecraft:hide_additional_tooltip\":{},\"minecraft:unbreakable\":{}}}",
  "damage": 0,
  "lore": [
    "{\"text\":\"\",\"extra\":[{\"text\":\"Health: \",\"color\":\"gray\"},{\"text\":\"+100\",\"color\":\"green\"}]}",
    "{\"text\":\"\",\"extra\":[{\"text\":\" \"},{\"text\":\"[☂]\",\"color\":\"dark_gray\"}]}",
    "{\"text\":\"\"}",
    "{\"text\":\"\",\"extra\":[{\"text\":\"Full Set Bonus: Peace Treaty \",\"color\":\"gold\"},{\"text\":\"(0/4)\",\"color\":\"gray\"}]}",
    "{\"text\":\"Gain immunity to Sea Creatures but\",\"color\":\"gray\"}",
    "{\"text\":\"they are immune to you and you can\",\"color\":\"gray\"}",
    "{\"text\":\"no longer catch them.\",\"color\":\"gray\"}",
    "{\"text\":\"\"}",
    "{\"text\":\"Tiered Bonus: Odger\u0027s Blessing (0/4)\",\"color\":\"dark_gray\"}",
    "{\"text\":\"\",\"extra\":[{\"text\":\"Grants \",\"color\":\"gray\"},{\"text\":\"+0♔ Trophy Fish Chance\",\"color\":\"gold\"},{\"text\":\".\",\"color\":\"gray\"}]}",
    "{\"text\":\" \"}",
    "{\"text\":\"\",\"extra\":[{\"text\":\"Full Set Bonus: Star Fisher \",\"color\":\"gold\"},{\"text\":\"(0/4)\",\"color\":\"gray\"}]}",
    "{\"text\":\"\",\"extra\":[{\"text\":\"Grants \",\"color\":\"gray\"},{\"text\":\"+0.4☂ Fishing Speed\",\"color\":\"aqua\"},{\"text\":\" per \",\"color\":\"gray\"},{\"text\":\"✪\",\"color\":\"gold\"}]}",
    "{\"text\":\"\",\"extra\":[{\"text\":\"Upgrade Star \",\"color\":\"gold\"},{\"text\":\"on your armor.\",\"color\":\"gray\"}]}",
    "{\"text\":\"\"}",
    "{\"text\":\"This item can be reforged!\",\"color\":\"dark_gray\"}",
    "{\"text\":\"\",\"extra\":[{\"text\":\"❣ \",\"color\":\"dark_red\"},{\"text\":\"Requires Adept Trophy Fisher.\",\"color\":\"red\"}]}",
    "{\"text\":\"\",\"extra\":[{\"text\":\"* \",\"color\":\"dark_gray\",\"bold\":true},{\"text\":\"Soulbound \",\"color\":\"dark_gray\"},{\"text\":\"**\",\"color\":\"dark_gray\",\"bold\":true}]}",
    "{\"text\":\"RARE LEGGINGS\",\"color\":\"blue\",\"bold\":true}"
  ],
  "internalname": "SILVER_HUNTER_LEGGINGS",
  "clickcommand": "",
  "crafttext": "",
  "modver": "Firmament 3.2.0-dev+mc1.21.5+gb028db5",
  "infoType": "WIKI_URL",
  "info": [
    "https://hypixel-skyblock.fandom.com/wiki/Silver_Hunter_Leggings",
    "https://wiki.hypixel.net/Silver_Hunter_Leggings"
  ],
  "format_version": 1,
  "conversion_method": "modern_1215_components",
  "converted_modern": true
}