{
  "itemid": "minecraft:player_head",
  "displayname": "{\"text\":\"Slice of Lemon Cheesecake\",\"color\":\"red\"}",
  "nbttag": "{\"id\":\"minecraft:player_head\",\"count\":1,\"components\":{\"minecraft:custom_name\":\"{\\\"text\\\":\\\"Slice of Lemon Cheesecake\\\",\\\"color\\\":\\\"red\\\"}\",\"minecraft:lore\":[\"{\\\"text\\\":\\\"Right-Click on a player on the\\\",\\\"color\\\":\\\"gray\\\"}\",\"{\\\"text\\\":\\\"\\\",\\\"extra\\\":[{\\\"text\\\":\\\"YELLOW\\\",\\\"color\\\":\\\"yellow\\\",\\\"bold\\\":true},{\\\"text\\\":\\\" team while holding this item\\\",\\\"color\\\":\\\"gray\\\"}]}\",\"{\\\"text\\\":\\\"to feed it to them!\\\",\\\"color\\\":\\\"gray\\\"}\",\"{\\\"text\\\":\\\"\\\"}\",\"{\\\"text\\\":\\\"Feeding a slice of cake to another\\\",\\\"color\\\":\\\"gray\\\"}\",\"{\\\"text\\\":\\\"\\\",\\\"extra\\\":[{\\\"text\\\":\\\"player gives both of you a \\\",\\\"color\\\":\\\"gray\\\"},{\\\"text\\\":\\\"reward\\\",\\\"color\\\":\\\"gold\\\"},{\\\"text\\\":\\\"!\\\",\\\"color\\\":\\\"gray\\\"}]}\",\"{\\\"text\\\":\\\"\\\"}\",\"{\\\"text\\\":\\\"\\\",\\\"extra\\\":[{\\\"text\\\":\\\"* \\\",\\\"color\\\":\\\"dark_gray\\\",\\\"bold\\\":true},{\\\"text\\\":\\\"Soulbound \\\",\\\"color\\\":\\\"dark_gray\\\"},{\\\"text\\\":\\\"*\\\",\\\"color\\\":\\\"dark_gray\\\",\\\"bold\\\":true}]}\",\"{\\\"text\\\":\\\"\\\",\\\"extra\\\":[{\\\"text\\\":\\\"X\\\",\\\"color\\\":\\\"dark_purple\\\",\\\"obfuscated\\\":true},{\\\"text\\\":\\\" Rift-Transferable \\\",\\\"color\\\":\\\"dark_purple\\\"},{\\\"text\\\":\\\"X\\\",\\\"color\\\":\\\"dark_purple\\\",\\\"obfuscated\\\":true}]}\",\"{\\\"text\\\":\\\"SPECIAL\\\",\\\"color\\\":\\\"red\\\",\\\"bold\\\":true}\"],\"minecraft:custom_data\":{\"id\":\"SLICE_OF_CHEESECAKE\",\"century_year_obtained\":400},\"minecraft:hide_additional_tooltip\":{}}}",
  "damage": 0,
  "lore": [
    "{\"text\":\"Right-Click on a player on the\",\"color\":\"gray\"}",
    "{\"text\":\"\",\"extra\":[{\"text\":\"YELLOW\",\"color\":\"yellow\",\"bold\":true},{\"text\":\" team while holding this item\",\"color\":\"gray\"}]}",
    "{\"text\":\"to feed it to them!\",\"color\":\"gray\"}",
    "{\"text\":\"\"}",
    "{\"text\":\"Feeding a slice of cake to another\",\"color\":\"gray\"}",
    "{\"text\":\"\",\"extra\":[{\"text\":\"player gives both of you a \",\"color\":\"gray\"},{\"text\":\"reward\",\"color\":\"gold\"},{\"text\":\"!\",\"color\":\"gray\"}]}",
    "{\"text\":\"\"}",
    "{\"text\":\"\",\"extra\":[{\"text\":\"* \",\"color\":\"dark_gray\",\"bold\":true},{\"text\":\"Soulbound \",\"color\":\"dark_gray\"},{\"text\":\"*\",\"color\":\"dark_gray\",\"bold\":true}]}",
    "{\"text\":\"\",\"extra\":[{\"text\":\"X\",\"color\":\"dark_purple\",\"obfuscated\":true},{\"text\":\" Rift-Transferable \",\"color\":\"dark_purple\"},{\"text\":\"X\",\"color\":\"dark_purple\",\"obfuscated\":true}]}",
    "{\"text\":\"SPECIAL\",\"color\":\"red\",\"bold\":true}"
  ],
  "internalname": "SLICE_OF_CHEESECAKE",
  "crafttext": "",
  "clickcommand": "",
  "modver": "",
  "infoType": "WIKI_URL",
  "info": [
    "https://wiki.hypixel.net/Slice_Of_Lemon_Cheesecake"
  ],
  "format_version": 1,
  "conversion_method": "modern_1215_components",
  "converted_modern": true
}