{
  "itemid": "minecraft:player_head",
  "displayname": "{\"text\":\"Zodd (NPC)\",\"color\":\"blue\"}",
  "nbttag": "{\"id\":\"minecraft:player_head\",\"count\":1,\"components\":{\"minecraft:custom_name\":\"{\\\"text\\\":\\\"Zodd (NPC)\\\",\\\"color\\\":\\\"blue\\\"}\",\"minecraft:lore\":[\"{\\\"text\\\":\\\"\\\",\\\"extra\\\":[{\\\"text\\\":\\\"This NPC can be found in \\\",\\\"color\\\":\\\"gray\\\"},{\\\"text\\\":\\\"The Catacombs\\\",\\\"color\\\":\\\"red\\\"},{\\\"text\\\":\\\".\\\",\\\"color\\\":\\\"gray\\\"}]}\"],\"minecraft:custom_data\":{\"id\":\"ZODD_NPC\"},\"minecraft:hide_additional_tooltip\":{}}}",
  "damage": 0,
  "lore": [
    "{\"text\":\"\",\"extra\":[{\"text\":\"This NPC can be found in \",\"color\":\"gray\"},{\"text\":\"The Catacombs\",\"color\":\"red\"},{\"text\":\".\",\"color\":\"gray\"}]}"
  ],
  "internalname": "ZODD_NPC",
  "clickcommand": "",
  "modver": "2.1.1-PRE",
  "recipes": [
    {
      "type": "npc_shop",
      "cost": [
        "SKYBLOCK_COIN:1000000"
      ],
      "result": "GENERAL_MEDALLION"
    }
  ],
  "crafttext": "",
  "infoType": "WIKI_URL",
  "info": [
    "https://hypixel-skyblock.fandom.com/wiki/Zodd",
    "https://wiki.hypixel.net/Zodd"
  ],
  "format_version": 1,
  "conversion_method": "modern_1215_components",
  "converted_modern": true
}